{
    "block_master_rubrikator":{
        "rubriks":[
            {
                "name": "Строительство",
                "count": "125",
                "color": "#37aae9",
                "podrubriks": [
                    {
                        "title":"Бани",
                        "url": "/master_rubrika/rubrika.html",
                        "count": "9"
                    },
                    {
                        "title":"Бассейны",
                        "url": "/master_rubrika/rubrika.html",
                        "count": "1"
                    },
                    {
                        "title":"Ландшафтный дизайн",
                        "url": "/master_rubrika/rubrika.html",
                        "count": "3"
                    },
                    {
                        "title":"Металлоконструкции",
                        "url": "/master_rubrika/rubrika.html",
                        "count": "28"
                    },
                    {
                        "title":"Печи и камины",
                        "url": "/master_rubrika/rubrika.html",
                        "count": "4"
                    }
                ]
            },
            {
                "name": "Ремонт квартир, домов",
                "count": "197",
                "color": "#37aae9",
                "podrubriks": [
                    {
                        "title":"Ремонт квартир",
                        "url": "/master_rubrika/rubrika.html",
                        "count": "105"
                    },
                    {
                        "title":"Реставрация ванн",
                        "url": "/master_rubrika/rubrika.html",
                        "count": "6"
                    },
                    {
                        "title":"Сантехники",
                        "url": "/master_rubrika/rubrika.html",
                        "count": "47"
                    },
                    {
                        "title":"Электрики",
                        "url": "/master_rubrika/rubrika.html",
                        "count": "39"
                    }
                ]
            },
            {
                "name": "Окна, двери, потолки",
                "count": "94",
                "color": "#37aae9",
                "podrubriks": [
                    {
                        "title":"Ремонт квартир",
                        "url": "/master_rubrika/rubrika.html",
                        "count": "105"
                    },
                    {
                        "title":"Реставрация ванн",
                        "url": "/master_rubrika/rubrika.html",
                        "count": "6"
                    },
                    {
                        "title":"Сантехники",
                        "url": "/master_rubrika/rubrika.html",
                        "count": "47"
                    },
                    {
                        "title":"Электрики",
                        "url": "/master_rubrika/rubrika.html",
                        "count": "39"
                    }
                ]
            },
            {
                "name": "Интерьер",
                "count": "99",
                "color": "#37aae9",
                "podrubriks": [
                    {
                        "title":"Ремонт квартир",
                        "url": "/master_rubrika/rubrika.html",
                        "count": "105"
                    },
                    {
                        "title":"Реставрация ванн",
                        "url": "/master_rubrika/rubrika.html",
                        "count": "6"
                    },
                    {
                        "title":"Сантехники",
                        "url": "/master_rubrika/rubrika.html",
                        "count": "47"
                    },
                    {
                        "title":"Электрики",
                        "url": "/master_rubrika/rubrika.html",
                        "count": "39"
                    }
                ]
            },
            {
                "name": "Врачи",
                "count": "56",
                "color": "#004d5a",
                "podrubriks": [
                    {
                        "title":"Ремонт квартир",
                        "url": "/master_rubrika/rubrika.html",
                        "count": "105"
                    },
                    {
                        "title":"Реставрация ванн",
                        "url": "/master_rubrika/rubrika.html",
                        "count": "6"
                    },
                    {
                        "title":"Сантехники",
                        "url": "/master_rubrika/rubrika.html",
                        "count": "47"
                    },
                    {
                        "title":"Электрики",
                        "url": "/master_rubrika/rubrika.html",
                        "count": "39"
                    }
                ]
            },
            {
                "name": "Оздоровительные услуги",
                "count": "14",
                "color": "#004d5a",
                "podrubriks": [
                    {
                        "title":"Ремонт квартир",
                        "url": "/master_rubrika/rubrika.html",
                        "count": "105"
                    },
                    {
                        "title":"Реставрация ванн",
                        "url": "/master_rubrika/rubrika.html",
                        "count": "6"
                    },
                    {
                        "title":"Сантехники",
                        "url": "/master_rubrika/rubrika.html",
                        "count": "47"
                    },
                    {
                        "title":"Электрики",
                        "url": "/master_rubrika/rubrika.html",
                        "count": "39"
                    }
                ]
            },
            {
                "name": "Спорт",
                "count": "7",
                "color": "#004d5a",
                "podrubriks": [
                    {
                        "title":"Ремонт квартир",
                        "url": "/master_rubrika/rubrika.html",
                        "count": "105"
                    },
                    {
                        "title":"Реставрация ванн",
                        "url": "/master_rubrika/rubrika.html",
                        "count": "6"
                    },
                    {
                        "title":"Сантехники",
                        "url": "/master_rubrika/rubrika.html",
                        "count": "47"
                    },
                    {
                        "title":"Электрики",
                        "url": "/master_rubrika/rubrika.html",
                        "count": "39"
                    }
                ]
            },
            {
                "name": "Организация праздников",
                "count": "115",
                "color": "#009344",
                "isNewCol": true,
                "podrubriks": [
                    {
                        "title":"Ремонт квартир",
                        "url": "/master_rubrika/rubrika.html",
                        "count": "105"
                    },
                    {
                        "title":"Реставрация ванн",
                        "url": "/master_rubrika/rubrika.html",
                        "count": "6"
                    },
                    {
                        "title":"Сантехники",
                        "url": "/master_rubrika/rubrika.html",
                        "count": "47"
                    },
                    {
                        "title":"Электрики",
                        "url": "/master_rubrika/rubrika.html",
                        "count": "39"
                    }
                ]
            },
            {
                "name": "Туризм",
                "count": "25",
                "color": "#009344",
                "podrubriks": [
                    {
                        "title":"Ремонт квартир",
                        "url": "/master_rubrika/rubrika.html",
                        "count": "105"
                    },
                    {
                        "title":"Реставрация ванн",
                        "url": "/master_rubrika/rubrika.html",
                        "count": "6"
                    },
                    {
                        "title":"Сантехники",
                        "url": "/master_rubrika/rubrika.html",
                        "count": "47"
                    },
                    {
                        "title":"Электрики",
                        "url": "/master_rubrika/rubrika.html",
                        "count": "39"
                    }
                ]
            },
            {
                "name": "Отдых",
                "count": "13",
                "color": "#009344",
                "podrubriks": [
                    {
                        "title":"Ремонт квартир",
                        "url": "/master_rubrika/rubrika.html",
                        "count": "105"
                    },
                    {
                        "title":"Реставрация ванн",
                        "url": "/master_rubrika/rubrika.html",
                        "count": "6"
                    },
                    {
                        "title":"Сантехники",
                        "url": "/master_rubrika/rubrika.html",
                        "count": "47"
                    },
                    {
                        "title":"Электрики",
                        "url": "/master_rubrika/rubrika.html",
                        "count": "39"
                    }
                ]
            },
            {
                "name": "Рестораны, кафе, бары",
                "count": "11",
                "color": "#009344",
                "podrubriks": [
                    {
                        "title":"Ремонт квартир",
                        "url": "/master_rubrika/rubrika.html",
                        "count": "105"
                    },
                    {
                        "title":"Реставрация ванн",
                        "url": "/master_rubrika/rubrika.html",
                        "count": "6"
                    },
                    {
                        "title":"Сантехники",
                        "url": "/master_rubrika/rubrika.html",
                        "count": "47"
                    },
                    {
                        "title":"Электрики",
                        "url": "/master_rubrika/rubrika.html",
                        "count": "39"
                    }
                ]
            },
            {
                "name": "Услуги для бизнеса",
                "count": "34",
                "color": "#f7931e",
                "podrubriks": [
                    {
                        "title":"Ремонт квартир",
                        "url": "/master_rubrika/rubrika.html",
                        "count": "105"
                    },
                    {
                        "title":"Реставрация ванн",
                        "url": "/master_rubrika/rubrika.html",
                        "count": "6"
                    },
                    {
                        "title":"Сантехники",
                        "url": "/master_rubrika/rubrika.html",
                        "count": "47"
                    },
                    {
                        "title":"Электрики",
                        "url": "/master_rubrika/rubrika.html",
                        "count": "39"
                    }
                ]
            },
            {
                "name": "Персональные консультации",
                "count": "26",
                "color": "#f7931e",
                "podrubriks": [
                    {
                        "title":"Ремонт квартир",
                        "url": "/master_rubrika/rubrika.html",
                        "count": "105"
                    },
                    {
                        "title":"Реставрация ванн",
                        "url": "/master_rubrika/rubrika.html",
                        "count": "6"
                    },
                    {
                        "title":"Сантехники",
                        "url": "/master_rubrika/rubrika.html",
                        "count": "47"
                    },
                    {
                        "title":"Электрики",
                        "url": "/master_rubrika/rubrika.html",
                        "count": "39"
                    }
                ]
            },
            {
                "name": "Красота",
                "count": "115",
                "color": "#8dc53e",
                "podrubriks": [
                    {
                        "title":"Ремонт квартир",
                        "url": "/master_rubrika/rubrika.html",
                        "count": "105"
                    },
                    {
                        "title":"Реставрация ванн",
                        "url": "/master_rubrika/rubrika.html",
                        "count": "6"
                    },
                    {
                        "title":"Сантехники",
                        "url": "/master_rubrika/rubrika.html",
                        "count": "47"
                    },
                    {
                        "title":"Электрики",
                        "url": "/master_rubrika/rubrika.html",
                        "count": "39"
                    }
                ]
            },
            {
                "name": "Одежда и обувь",
                "count": "115",
                "color": "#8dc53e",
                "podrubriks": [
                    {
                        "title":"Ремонт квартир",
                        "url": "/master_rubrika/rubrika.html",
                        "count": "105"
                    },
                    {
                        "title":"Реставрация ванн",
                        "url": "/master_rubrika/rubrika.html",
                        "count": "6"
                    },
                    {
                        "title":"Сантехники",
                        "url": "/master_rubrika/rubrika.html",
                        "count": "47"
                    },
                    {
                        "title":"Электрики",
                        "url": "/master_rubrika/rubrika.html",
                        "count": "39"
                    }
                ]
            },
            {
                "name": "Установка и ремонт техники",
                "count": "115",
                "color": "#ee4136",
                "isNewCol": true,
                "podrubriks": [
                    {
                        "title":"Ремонт квартир",
                        "url": "/master_rubrika/rubrika.html",
                        "count": "105"
                    },
                    {
                        "title":"Реставрация ванн",
                        "url": "/master_rubrika/rubrika.html",
                        "count": "6"
                    },
                    {
                        "title":"Сантехники",
                        "url": "/master_rubrika/rubrika.html",
                        "count": "47"
                    },
                    {
                        "title":"Электрики",
                        "url": "/master_rubrika/rubrika.html",
                        "count": "39"
                    }
                ]
            },
            {
                "name": "Автоуслуги",
                "count": "96",
                "color": "#00a79d",
                "podrubriks": [
                    {
                        "title":"Ремонт квартир",
                        "url": "/master_rubrika/rubrika.html",
                        "count": "105"
                    },
                    {
                        "title":"Реставрация ванн",
                        "url": "/master_rubrika/rubrika.html",
                        "count": "6"
                    },
                    {
                        "title":"Сантехники",
                        "url": "/master_rubrika/rubrika.html",
                        "count": "47"
                    },
                    {
                        "title":"Электрики",
                        "url": "/master_rubrika/rubrika.html",
                        "count": "39"
                    }
                ]
            },
            {
                "name": "Доставка",
                "count": "4",
                "color": "#00a79d",
                "podrubriks": [
                    {
                        "title":"Ремонт квартир",
                        "url": "/master_rubrika/rubrika.html",
                        "count": "105"
                    },
                    {
                        "title":"Реставрация ванн",
                        "url": "/master_rubrika/rubrika.html",
                        "count": "6"
                    },
                    {
                        "title":"Сантехники",
                        "url": "/master_rubrika/rubrika.html",
                        "count": "47"
                    },
                    {
                        "title":"Электрики",
                        "url": "/master_rubrika/rubrika.html",
                        "count": "39"
                    }
                ]
            },
            {
                "name": "Курсы",
                "count": "33",
                "color": "#7e3e97",
                "podrubriks": [
                    {
                        "title":"Ремонт квартир",
                        "url": "/master_rubrika/rubrika.html",
                        "count": "105"
                    },
                    {
                        "title":"Реставрация ванн",
                        "url": "/master_rubrika/rubrika.html",
                        "count": "6"
                    },
                    {
                        "title":"Сантехники",
                        "url": "/master_rubrika/rubrika.html",
                        "count": "47"
                    },
                    {
                        "title":"Электрики",
                        "url": "/master_rubrika/rubrika.html",
                        "count": "39"
                    }
                ]
            },
            {
                "name": "Недвижимость",
                "count": "38",
                "color": "#9e1f62",
                "podrubriks": [
                    {
                        "title":"Ремонт квартир",
                        "url": "/master_rubrika/rubrika.html",
                        "count": "105"
                    },
                    {
                        "title":"Реставрация ванн",
                        "url": "/master_rubrika/rubrika.html",
                        "count": "6"
                    },
                    {
                        "title":"Сантехники",
                        "url": "/master_rubrika/rubrika.html",
                        "count": "47"
                    },
                    {
                        "title":"Электрики",
                        "url": "/master_rubrika/rubrika.html",
                        "count": "39"
                    }
                ]
            },
            {
                "name": "Ритуальные услуги",
                "count": "10",
                "color": "#7e3e97",
                "podrubriks": [
                    {
                        "title":"Ремонт квартир",
                        "url": "/master_rubrika/rubrika.html",
                        "count": "105"
                    },
                    {
                        "title":"Реставрация ванн",
                        "url": "/master_rubrika/rubrika.html",
                        "count": "6"
                    },
                    {
                        "title":"Сантехники",
                        "url": "/master_rubrika/rubrika.html",
                        "count": "47"
                    },
                    {
                        "title":"Электрики",
                        "url": "/master_rubrika/rubrika.html",
                        "count": "39"
                    }
                ]
            },
            {
                "name": "Другие услуги",
                "count": "37",
                "color": "#6395A7",
                "podrubriks": [
                    {
                        "title":"Ремонт квартир",
                        "url": "/master_rubrika/rubrika.html",
                        "count": "105"
                    },
                    {
                        "title":"Реставрация ванн",
                        "url": "/master_rubrika/rubrika.html",
                        "count": "6"
                    },
                    {
                        "title":"Сантехники",
                        "url": "/master_rubrika/rubrika.html",
                        "count": "47"
                    },
                    {
                        "title":"Электрики",
                        "url": "/master_rubrika/rubrika.html",
                        "count": "39"
                    }
                ]
            }
        ]
    }
}